eec/__init__.py
eec/_eec.cp37-win_amd64.pyd
eec/eec.py
EnergyEnergyCorrelators-1.1.1.dist-info/LICENSE
EnergyEnergyCorrelators-1.1.1.dist-info/METADATA
EnergyEnergyCorrelators-1.1.1.dist-info/WHEEL
EnergyEnergyCorrelators-1.1.1.dist-info/top_level.txt
EnergyEnergyCorrelators-1.1.1.dist-info/RECORD
