Metadata-Version: 2.1
Name: EnergyEnergyCorrelators
Version: 1.1.1
Summary: EEC computations in python
Home-page: https://github.com/pkomiske/EnergyEnergyCorrelators
Author: Patrick T. Komiske III
Author-email: pkomiske@mit.edu
License: GPL-3.0
Keywords: eec,energy-energy correlator,irc-safe,infrared safety,operator product expansion,weighted cross section
Platform: UNKNOWN
Requires-Python: >=3.5
